methodflow/__init__.py
methodflow/pipeline.py
methodflow-0.0.1a1.dist-info/LICENSE.txt
methodflow-0.0.1a1.dist-info/METADATA
methodflow-0.0.1a1.dist-info/WHEEL
methodflow-0.0.1a1.dist-info/top_level.txt
methodflow-0.0.1a1.dist-info/RECORD
